number_transcription/__init__.py
number_transcription/english/__init__.py
number_transcription/english/conversion.py
number_transcription/english/enums.py
number_transcription/english/storage.py
number_transcription/english/tests.py
number_transcription/enums.py
number_transcription/russian/__init__.py
number_transcription/russian/conversion.py
number_transcription/russian/enums.py
number_transcription/russian/storage.py
number_transcription/russian/tests.py
number_transcription-1.1.0.dist-info/METADATA
number_transcription-1.1.0.dist-info/WHEEL
number_transcription-1.1.0.dist-info/RECORD
