Metadata-Version: 2.1
Name: number-transcription
Version: 1.1.0
Summary: Multilanguage library for conversion numbers to words description
License: MIT
Author: Oleg Yurchik
Author-email: oleg@yurchik.space
Requires-Python: >=3.10,<4.0
Classifier: License :: OSI Approved :: MIT License
Classifier: Programming Language :: Python :: 3
Classifier: Programming Language :: Python :: 3.10
Classifier: Programming Language :: Python :: 3.11
